PyQt5/QtWebKitWidgets.so
PyQt5/QtWebKit.so
PyQt5/Qt/qml/QtWebKit/qmldir
PyQt5/Qt/qml/QtWebKit/plugins.qmltypes
PyQt5/Qt/qml/QtWebKit/libqmlwebkitplugin.so
PyQt5/Qt/qml/QtWebKit/experimental/qmldir
PyQt5/Qt/qml/QtWebKit/experimental/libqmlwebkitexperimentalplugin.so
PyQt5/Qt/libexec/QtWebStorageProcess
PyQt5/Qt/libexec/QtWebNetworkProcess
PyQt5/Qt/libexec/QtWebProcess
PyQt5/Qt/lib/QtWebKitWidgets.framework/QtWebKitWidgets
PyQt5/Qt/lib/QtWebKitWidgets.framework/Versions/5/QtWebKitWidgets
PyQt5/Qt/lib/QtWebKitWidgets.framework/Versions/5/Resources/Info.plist
PyQt5/Qt/lib/QtWebKitWidgets.framework/Versions/5/Headers/QWebInspector
PyQt5/Qt/lib/QtWebKitWidgets.framework/Versions/5/Headers/QWebFrame
PyQt5/Qt/lib/QtWebKitWidgets.framework/Versions/5/Headers/qtwebkitwidgetsversion.h
PyQt5/Qt/lib/QtWebKitWidgets.framework/Versions/5/Headers/qwebframe.h
PyQt5/Qt/lib/QtWebKitWidgets.framework/Versions/5/Headers/qwebinspector.h
PyQt5/Qt/lib/QtWebKitWidgets.framework/Versions/5/Headers/qgraphicswebview.h
PyQt5/Qt/lib/QtWebKitWidgets.framework/Versions/5/Headers/QWebPage
PyQt5/Qt/lib/QtWebKitWidgets.framework/Versions/5/Headers/QtWebKitWidgets
PyQt5/Qt/lib/QtWebKitWidgets.framework/Versions/5/Headers/qwebpage.h
PyQt5/Qt/lib/QtWebKitWidgets.framework/Versions/5/Headers/QGraphicsWebView
PyQt5/Qt/lib/QtWebKitWidgets.framework/Versions/5/Headers/QtWebKitWidgetsDepends
PyQt5/Qt/lib/QtWebKitWidgets.framework/Versions/5/Headers/QtWebKitWidgetsVersion
PyQt5/Qt/lib/QtWebKitWidgets.framework/Versions/5/Headers/QWebHitTestResult
PyQt5/Qt/lib/QtWebKitWidgets.framework/Versions/5/Headers/qwebview.h
PyQt5/Qt/lib/QtWebKitWidgets.framework/Versions/5/Headers/QWebView
PyQt5/Qt/lib/QtWebKitWidgets.framework/Versions/5/Headers/5.212.0/QtWebKitWidgets/private/qwebframe_p.h
PyQt5/Qt/lib/QtWebKitWidgets.framework/Versions/5/Headers/5.212.0/QtWebKitWidgets/private/qwebpage_p.h
PyQt5/Qt/lib/QtWebKitWidgets.framework/Versions/5/Headers/5.212.0/QtWebKitWidgets/private/qwebviewaccessible_p.h
PyQtWebKit-5.15.2.dist-info/INSTALLER
PyQtWebKit-5.15.2.dist-info/METADATA
PyQtWebKit-5.15.2.dist-info/RECORD
