Metadata-Version: 1.0
Name: PyQtWebKit
Version: 5.15.2
Summary: Python bindings for the Qt WebKit library
Home-page: https://github.com/PyQt5/PyQtWebKit
Author: Irony
Author-email: 892768447@qq.com
License: GPL v3
Platform: UNIX
Platform: Windows
Platform: MacOS
Classifier: Programming Language :: Python :: 3.5
Classifier: Programming Language :: Python :: 3.6
Classifier: Programming Language :: Python :: 3.7
Classifier: Programming Language :: Python :: 3.8
Classifier: Programming Language :: Python :: 3.9
Requires-Dist: PyQt5 (==5.15.2)
